biztime/__init__.py
biztime/biztime.py
biztime/biztime_test.py
biztime-0.0.8.dist-info/DESCRIPTION.rst
biztime-0.0.8.dist-info/METADATA
biztime-0.0.8.dist-info/RECORD
biztime-0.0.8.dist-info/WHEEL
biztime-0.0.8.dist-info/metadata.json
biztime-0.0.8.dist-info/top_level.txt
