Metadata-Version: 2.0
Name: biztime
Version: 0.0.8
Summary: Utility for calculating the total working time between given dates/times.
Home-page: https://github.com/austen0/biztime
Author: austen0
Author-email: austen@cas3y.com
License: UNKNOWN
Platform: UNKNOWN
